api_Rocket/__init__.py
api_Rocket/clients/async_client.py
api_Rocket/clients/client.py
api_Rocket/clients/__pycache__/async_client.cpython-38.pyc
api_Rocket/clients/__pycache__/client.cpython-38.pyc
api_Rocket/clients/exception/exceptions.py
api_Rocket/clients/exception/__pycache__/exceptions.cpython-38.pyc
api_Rocket-1.6.4.dist-info/METADATA
api_Rocket-1.6.4.dist-info/WHEEL
api_Rocket-1.6.4.dist-info/top_level.txt
api_Rocket-1.6.4.dist-info/RECORD
