Metadata-Version: 2.1
Name: api-Rocket
Version: 1.6.4
Summary: api for ton rocket
Home-page: UNKNOWN
Author: Redpiar
Author-email: Regeonwix@gmail.com
License: UNKNOWN
Platform: UNKNOWN
Classifier: Programming Language :: Python :: 3
Classifier: License :: OSI Approved :: MIT License
Classifier: Operating System :: OS Independent
Requires-Python: >=3.6
